SimplifyPython/__init__.py
SimplifyPython/crypto.py
SimplifyPython/file.py
SimplifyPython/flask.py
SimplifyPython/json.py
SimplifyPython/paste.py
SimplifyPython/print.py
SimplifyPython-0.0.19.dist-info/LICENSE
SimplifyPython-0.0.19.dist-info/METADATA
SimplifyPython-0.0.19.dist-info/WHEEL
SimplifyPython-0.0.19.dist-info/top_level.txt
SimplifyPython-0.0.19.dist-info/RECORD
