Metadata-Version: 2.1
Name: SimplifyPython
Version: 0.0.19
Summary: Simplifys aspects of python
Home-page: https://github.com/Necrownyx/SimplifyPython
Author: Isaac
Author-email: necrownyx@outlook.com
License: UNKNOWN
Project-URL: Bug Tracker, https://github.com/Necrownyx/SimplifyPython/issues
Platform: UNKNOWN
Classifier: Programming Language :: Python :: 3
Classifier: License :: OSI Approved :: MIT License
Classifier: Operating System :: OS Independent
Requires-Python: >=3.6
License-File: LICENSE
Requires-Dist: PingServer (==1.0.1)
Requires-Dist: requests
Requires-Dist: cryptography
